webscp
