Metadata-Version: 1.2
Name: webscp
Version: 1.0.2
Summary: Scrape and email modules to an email id.
Home-page: UNKNOWN
Author: Govind Choudhary, Sreejith Subhash
Author-email: govind2220000@gmail.com, sreejithsubhash198@gmail.com
License: UNKNOWN
Project-URL: Documentation, https://github.com/govind2220000/image_scraper
Project-URL: Source, https://github.com/govind2220000/image_scraper
Project-URL: Tracker, https://github.com/govind2220000/image_scraper/issues
Platform: UNKNOWN
Requires-Python: >=3
